thrasks/__init__.py
thrasks/_core.py
thrasks-0.1.0.post1.dist-info/WHEEL
thrasks-0.1.0.post1.dist-info/METADATA
thrasks-0.1.0.post1.dist-info/RECORD
