Metadata-Version: 2.4
Name: thrasks
Version: 0.1.0.post1
Summary: Threaded async tasks for free-threaded Python 3.14 - run coroutines across thread pools
Keywords: concurrency,parallelism,concurrent,parallel,task,threads,threading,async
Author: Jakub Gajski
Author-email: Jakub Gajski <jakub.gajski@gmail.com>
License-Expression: MIT
Requires-Dist: pytest>=8.0.0 ; extra == 'dev'
Requires-Dist: pytest-asyncio>=0.23.0 ; extra == 'dev'
Requires-Python: >=3.14
Project-URL: Repository, https://github.com/jakubgajski/thrasks
Provides-Extra: dev
